pylibsshext/_libssh_version.cpython-312-darwin.so
pylibsshext/_libssh_version.pyx
pylibsshext/scp.pxd
pylibsshext/errors.pyx
pylibsshext/_version.py
pylibsshext/scp.cpython-312-darwin.so
pylibsshext/channel.pxd
pylibsshext/__init__.py
pylibsshext/sftp.pyx
pylibsshext/session.pyx
pylibsshext/session.pxd
pylibsshext/sftp.pxd
pylibsshext/sftp.cpython-312-darwin.so
pylibsshext/.gitignore
pylibsshext/session.cpython-312-darwin.so
pylibsshext/channel.pyx
pylibsshext/channel.cpython-312-darwin.so
pylibsshext/errors.pxd
pylibsshext/scp.pyx
pylibsshext/errors.cpython-312-darwin.so
pylibsshext/_scm_version.py
pylibsshext/includes/libssh.pxd
pylibsshext/includes/__init__.py
pylibsshext/includes/sftp.pxd
pylibsshext/includes/callbacks.pxd
pylibsshext/.dylibs/libcrypto.3.dylib
pylibsshext/.dylibs/libssh.4.10.2.dylib
ansible_pylibssh-1.3.0.dist-info/RECORD
ansible_pylibssh-1.3.0.dist-info/WHEEL
ansible_pylibssh-1.3.0.dist-info/LICENSE.rst
ansible_pylibssh-1.3.0.dist-info/top_level.txt
ansible_pylibssh-1.3.0.dist-info/METADATA
