Metadata-Version: 2.1
Name: ansible-pylibssh
Version: 1.3.0
Summary: Python bindings for libssh client specific to Ansible use case
Home-page: https://github.com/ansible/pylibssh
Author: Ansible, Inc.
Author-email: info+github/ansible/pylibssh@ansible.com
License: LGPLv2+
Project-URL: Bug Tracker, https://github.com/ansible/pylibssh/issues
Project-URL: CI: GitHub Workflows, https://github.com/ansible/pylibssh/actions?query=branch:devel
Project-URL: Code of Conduct, https://docs.ansible.com/ansible/latest/community/code_of_conduct.html
Project-URL: Docs: RTD, https://ansible-pylibssh.rtfd.io/
Project-URL: Source Code, https://github.com/ansible/pylibssh
Keywords: cython,cext,libssh
Classifier: Development Status :: 2 - Pre-Alpha
Classifier: License :: OSI Approved :: GNU Lesser General Public License v2 or later (LGPLv2+)
Classifier: Operating System :: MacOS
Classifier: Operating System :: POSIX :: Linux
Classifier: Programming Language :: Python :: 3
Classifier: Programming Language :: Python :: 3.9
Classifier: Programming Language :: Python :: 3.10
Classifier: Programming Language :: Python :: 3.11
Classifier: Programming Language :: Python :: 3.12
Classifier: Programming Language :: Cython
Classifier: Topic :: Software Development :: Libraries :: Python Modules
Classifier: Topic :: Security
Requires-Python: >=3.9
License-File: LICENSE.rst
